cachetory/__init__.py
cachetory/backends/__init__.py
cachetory/backends/async_/__init__.py
cachetory/backends/async_/django.py
cachetory/backends/async_/dummy.py
cachetory/backends/async_/memory.py
cachetory/backends/async_/redis.py
cachetory/backends/sync/__init__.py
cachetory/backends/sync/django.py
cachetory/backends/sync/dummy.py
cachetory/backends/sync/memory.py
cachetory/backends/sync/redis.py
cachetory/caches/__init__.py
cachetory/caches/async_.py
cachetory/caches/private.py
cachetory/caches/sync.py
cachetory/decorators/__init__.py
cachetory/decorators/async_.py
cachetory/decorators/shared.py
cachetory/decorators/sync.py
cachetory/interfaces/__init__.py
cachetory/interfaces/backends/__init__.py
cachetory/interfaces/backends/async_.py
cachetory/interfaces/backends/private.py
cachetory/interfaces/backends/sync.py
cachetory/interfaces/serializers.py
cachetory/private/__init__.py
cachetory/private/asyncio.py
cachetory/private/datetime.py
cachetory/private/functools.py
cachetory/private/typing.py
cachetory/py.typed
cachetory/serializers/__init__.py
cachetory/serializers/chained.py
cachetory/serializers/compressors/__init__.py
cachetory/serializers/compressors/zlib.py
cachetory/serializers/compressors/zstd.py
cachetory/serializers/json.py
cachetory/serializers/msgpack.py
cachetory/serializers/noop.py
cachetory/serializers/pickle.py
cachetory/shortcuts/__init__.py
cachetory/shortcuts/async_.py
cachetory/shortcuts/sync.py
cachetory-3.5.1.dist-info/LICENSE
cachetory-3.5.1.dist-info/METADATA
cachetory-3.5.1.dist-info/WHEEL
cachetory-3.5.1.dist-info/RECORD
