Metadata-Version: 2.1
Name: cachetory
Version: 3.5.1
Summary: Caching library with support for multiple cache backends
Home-page: https://github.com/kpn/cachetory
License: Apache-2.0
Keywords: cache
Author: Pavel Perestoronin
Author-email: pavel.perestoronin@kpn.com
Requires-Python: >=3.9.0,<4.0.0
Classifier: Development Status :: 5 - Production/Stable
Classifier: Environment :: Web Environment
Classifier: Intended Audience :: Developers
Classifier: License :: OSI Approved :: Apache Software License
Classifier: Operating System :: OS Independent
Classifier: Programming Language :: Python
Classifier: Programming Language :: Python :: 3
Classifier: Programming Language :: Python :: 3.9
Classifier: Programming Language :: Python :: 3.10
Classifier: Programming Language :: Python :: 3.11
Classifier: Programming Language :: Python :: 3.12
Classifier: Programming Language :: Python :: 3.13
Classifier: Programming Language :: Python :: 3 :: Only
Classifier: Topic :: Internet :: WWW/HTTP
Classifier: Typing :: Typed
Provides-Extra: django
Provides-Extra: ormsgpack
Provides-Extra: redis
Provides-Extra: zstd
Requires-Dist: django (>=4.0.0,<6.0.0) ; extra == "django"
Requires-Dist: ormsgpack (>=1.4.0,<2.0.0) ; (platform_python_implementation == "CPython") and (extra == "ormsgpack")
Requires-Dist: pydantic (>=2.0.0,<3.0.0)
Requires-Dist: redis (>=4.4.2,<7.0.0) ; extra == "redis"
Requires-Dist: typing-extensions (>=4.4.0,<5.0.0)
Requires-Dist: zstd (>=1.5.2.6,<2.0.0.0) ; extra == "zstd"
Project-URL: Repository, https://github.com/kpn/cachetory
